{
  "$schema": "https://json-schema.org/draft/2020-12/schema",
  "title": "B2 conformance vector (canonical, all areas)",
  "description": "One schema across every B2 area, per the step-4 protocol agreement (writer proposal event 4665fea7, reviewer CONCUR event c79b0591). Per-area vector files are arrays of these. Lives in docs/core during step 4; moves into the B2 suite package when it opens (path pending the legacy/ quarantine move).",
  "type": "object",
  "required": ["id", "ruleId", "area", "authorityTier", "sources", "kind", "inputs", "expected", "status"],
  "properties": {
    "id": { "type": "string", "description": "e.g. Q3-neg-01 — ruleId, kind, ordinal", "pattern": "^[A-Z]+[0-9]+[a-z]?-(neg|pos)-[0-9]{2}$" },
    "ruleId": { "type": "string", "description": "B2_KERNEL_HARDENING.md rule id (A1..G11)" },
    "area": { "type": "string", "description": "area name as in the hardening doc" },
    "authorityTier": { "type": "string", "enum": ["normative", "candidate", "provisional"], "description": "tier of the authority the expected verdict derives from; provisional = depends on a provisional decision" },
    "sources": { "type": "array", "items": { "type": "string" }, "minItems": 1, "description": "doc path + section per citation, matching the rule's sources" },
    "decisionDeps": { "type": "array", "items": { "type": "string" }, "description": "named decisions the expected verdict depends on, e.g. da-windows (#49)" },
    "params": { "type": "object", "description": "consensus parameters this vector instantiates (e.g. K/W/C); placeholders flagged as launch-freeze" },
    "inputs": { "type": "object", "description": "the pure-predicate inputs: event bytes / prior state / chain facts / witnessed evidence, per the kernel signature in the hardening doc" },
    "expected": { "type": "object", "description": "expected verdict object (accept/reject + reason code)" },
    "kind": { "type": "string", "enum": ["negative", "positive"] },
    "flipMarker": { "type": ["object", "null"], "description": "present iff authorityTier=provisional: { decision, flipsTo } — what this vector becomes if DK rules the other way", "properties": { "decision": { "type": "string" }, "flipsTo": { "type": "string" } } },
    "status": { "type": "string", "enum": ["proposed", "locked", "flipped", "retired"], "description": "locked = survived the per-area review gate" },
    "attackFlagRef": { "type": ["string", "null"], "description": "worklist row this vector discharges, if any" }
  }
}
